{"is_source_file": true, "format": "JavaScript (React JSX)", "description": "React component for displaying and managing workflow progress, including step statuses, actions, and modals for pausing and requesting changes.", "external_files": ["../common/Modal", "../../domain/workflow", "../../state/workflow", "../../state/messages", "react", "react-i18next"], "external_methods": ["useTranslation", "Modal", "useWorkflow", "WorkflowStepStatus", "useAppMessages"], "published": ["default"], "classes": [], "methods": [{"name": "statusKey", "description": "Generates a localization key for a given workflow status."}, {"name": "statusBadgeClass", "description": "Returns CSS class names for status badges based on status and whether the step is current."}, {"name": "canAdvance", "description": "Checks if the current step can be advanced (approved)."}, {"name": "isPaused", "description": "Checks if the current step is paused."}], "calls": ["useTranslation", "pushMessage", "useWorkflow", "useMemo", "useState", "useRef", "useEffect", "actions.advanceToNext", "actions.setCurrentStep", "actions.resumeWorkflow", "actions.pauseWorkflow", "actions.approveStep", "actions.requestChanges"], "search-terms": ["WorkflowProgressPanel", "workflow step statuses", "pause modal", "request changes modal", "workflow actions", "React workflow component"], "state": 2, "file_id": 41, "knowledge_revision": 118, "git_revision": "4ee3bd9677ec10ef90eada0c70339c25df1d73d4", "revision_history": [{"107": "4ee3bd9677ec10ef90eada0c70339c25df1d73d4"}, {"118": "4ee3bd9677ec10ef90eada0c70339c25df1d73d4"}], "ctags": [], "filename": "content_strategy_frontend/src/components/workflow/WorkflowProgressPanel.js", "format-version": 4, "code-base-name": "https://github.com/kavia-common/cultural-content-creator-for-hispanic-communities-227577-228328.git:kavia-main"}